{
  "id": "a1603d56-fadd-4621-8458-3629ff0930fa",
  "prevId": "00000000-0000-0000-0000-000000000000",
  "version": "7",
  "dialect": "postgresql",
  "tables": {
    "public.membership": {
      "name": "membership",
      "schema": "",
      "columns": {
        "id": {
          "name": "id",
          "type": "text",
          "primaryKey": true,
          "notNull": true
        },
        "name": {
          "name": "name",
          "type": "text",
          "primaryKey": false,
          "notNull": true
        },
        "price": {
          "name": "price",
          "type": "bigint",
          "primaryKey": false,
          "notNull": true
        },
        "originalPrice": {
          "name": "originalPrice",
          "type": "bigint",
          "primaryKey": false,
          "notNull": true
        },
        "currency": {
          "name": "currency",
          "type": "text",
          "primaryKey": false,
          "notNull": true
        },
        "period": {
          "name": "period",
          "type": "text",
          "primaryKey": false,
          "notNull": true
        },
        "features": {
          "name": "features",
          "type": "text[]",
          "primaryKey": false,
          "notNull": true
        },
        "createdAt": {
          "name": "createdAt",
          "type": "timestamp with time zone",
          "primaryKey": false,
          "notNull": true,
          "default": "now()"
        },
        "updatedAt": {
          "name": "updatedAt",
          "type": "timestamp with time zone",
          "primaryKey": false,
          "notNull": true,
          "default": "now()"
        }
      },
      "indexes": {},
      "foreignKeys": {},
      "compositePrimaryKeys": {},
      "uniqueConstraints": {},
      "policies": {},
      "checkConstraints": {},
      "isRLSEnabled": false
    }
  },
  "enums": {},
  "schemas": {},
  "sequences": {},
  "roles": {},
  "policies": {},
  "views": {},
  "_meta": {
    "columns": {},
    "schemas": {},
    "tables": {}
  }
}